XinlingdeBenzhi/Dockerfile
XinlingdeBenzhi/README.md
XinlingdeBenzhi/__init__.py
XinlingdeBenzhi/__main__.py
XinlingdeBenzhi/file.epub
XinlingdeBenzhi/index.html
XinlingdeBenzhi/css/__init__.py
XinlingdeBenzhi/css/annotations.css
XinlingdeBenzhi/css/main.css
XinlingdeBenzhi/css/normalize.css
XinlingdeBenzhi/css/popup.css
XinlingdeBenzhi/font/__init__.py
XinlingdeBenzhi/font/fontello.eot
XinlingdeBenzhi/font/fontello.svg
XinlingdeBenzhi/font/fontello.ttf
XinlingdeBenzhi/font/fontello.woff
XinlingdeBenzhi/img/__init__.py
XinlingdeBenzhi/img/annotator-glyph-sprite.png
XinlingdeBenzhi/img/annotator-icon-sprite.png
XinlingdeBenzhi/img/apple-touch-icon.png
XinlingdeBenzhi/img/cancelfullscreen.png
XinlingdeBenzhi/img/close.png
XinlingdeBenzhi/img/fullscreen.png
XinlingdeBenzhi/img/loader.gif
XinlingdeBenzhi/img/menu-icon.png
XinlingdeBenzhi/img/save.png
XinlingdeBenzhi/img/saved.png
XinlingdeBenzhi/img/settings-s.png
XinlingdeBenzhi/img/settings.png
XinlingdeBenzhi/img/star.png
XinlingdeBenzhi/js/__init__.py
XinlingdeBenzhi/js/epub.js
XinlingdeBenzhi/js/epub.min.js
XinlingdeBenzhi/js/epub.min.map
XinlingdeBenzhi/js/hooks.min.js
XinlingdeBenzhi/js/hooks.min.map
XinlingdeBenzhi/js/reader.js
XinlingdeBenzhi/js/reader.js.map
XinlingdeBenzhi/js/reader.min.js
XinlingdeBenzhi/js/reader.min.map
XinlingdeBenzhi/js/hooks/__init__.py
XinlingdeBenzhi/js/hooks/extensions/__init__.py
XinlingdeBenzhi/js/hooks/extensions/highlight.js
XinlingdeBenzhi/js/libs/__init__.py
XinlingdeBenzhi/js/libs/jquery.min.js
XinlingdeBenzhi/js/libs/localforage.min.js
XinlingdeBenzhi/js/libs/screenfull.js
XinlingdeBenzhi/js/libs/screenfull.min.js
XinlingdeBenzhi/js/libs/zip.min.js
XinlingdeBenzhi/js/plugins/__init__.py
XinlingdeBenzhi/js/plugins/hypothesis.js
XinlingdeBenzhi/js/plugins/search.js
xinlingde_benzhi-2022.10.9.1.dist-info/METADATA
xinlingde_benzhi-2022.10.9.1.dist-info/WHEEL
xinlingde_benzhi-2022.10.9.1.dist-info/entry_points.txt
xinlingde_benzhi-2022.10.9.1.dist-info/top_level.txt
xinlingde_benzhi-2022.10.9.1.dist-info/RECORD
